setup.py
scripts/test.py
ustcnlp/__init__.py
ustcnlp/dictionary.py
ustcnlp/essay.py
ustcnlp/manager.py
ustcnlp/statistics.py
ustcnlp.egg-info/PKG-INFO
ustcnlp.egg-info/SOURCES.txt
ustcnlp.egg-info/dependency_links.txt
ustcnlp.egg-info/top_level.txt
ustcnlp/corpus/__init__.py
ustcnlp/corpus/custom.py
ustcnlp/corpus/trd.py
ustcnlp/model/__init__.py
ustcnlp/model/svm.py
ustcnlp/model/svmutil.py
ustcnlp/utils/__init__.py
ustcnlp/utils/basic.py
ustcnlp/utils/cpp.py
ustcnlp/utils/file.py
ustcnlp/utils/run.py