Metadata-Version: 1.0
Name: ustcnlp
Version: 0.10
Summary: Automatic scoring using nlp
Home-page: http://www.ustc.edu.cn
Author: Cheng Ding, WeiWei Duan
Author-email: sa514004@mail.ustc.edu.cn
License: MIT
Platform: UNKNOWN
